napari_stereoTis/__init__.py
napari_stereoTis/_background.py
napari_stereoTis/_cellAgg.py
napari_stereoTis/_cellpose.py
napari_stereoTis/_signature.py
napari_stereoTis/_utils.py
napari_stereoTis/napari.yaml
napari_stereotis-0.3.0.dist-info/licenses/LICENSE
napari_stereotis-0.3.0.dist-info/METADATA
napari_stereotis-0.3.0.dist-info/WHEEL
napari_stereotis-0.3.0.dist-info/entry_points.txt
napari_stereotis-0.3.0.dist-info/top_level.txt
napari_stereotis-0.3.0.dist-info/RECORD
