Metadata-Version: 2.4
Name: napari-stereoTis
Version: 0.3.0
Summary: Used to mask cells or tissues for spatial transcriptomes
Author: Qi Fang
Author-email: Qi Fang <fangqi@genomics.cn>
Requires-Python: >=3.10
License-File: LICENSE
Requires-Dist: napari[all]
Requires-Dist: magicgui
Requires-Dist: numpy
Requires-Dist: scikit-image
Requires-Dist: opencv-python
Requires-Dist: pandas
Requires-Dist: matplotlib
Dynamic: license-file
